Workbook

Sheet Resumo Geral
B2: ROVER ESP32-S3 4WD — PLANEJAMENTO CONSOLIDADO DE COMPRAS
B3: Revisado em 13/10/2026. Totais incluem estimativas do ML; compra ainda tem pendências.
B5: TOTAL COM ESTIMATIVAS | D5: À VISTA COM ESTIMATIVAS | F5: ECONOMIA TOTAL À VISTA
B6: ='UsinaInfo'!F20+'Mercado Livre'!F14+'Curto Circuito'!F10 | D6: ='UsinaInfo'!G20+'Mercado Livre'!G14+'Curto Circuito'!G10 | F6: =B6-D6
B9: CONSOLIDAÇÃO POR FORNECEDOR / LOJA
B10: Loja / Plataforma | C10: Escopo dos Componentes | D10: Desconto À Vista | E10: Subtotal Cartão | F10: Subtotal Pix/Boleto | G10: Economia
B11: UsinaInfo | C11: Bancada térmica, telemetria, antena 3dBi, display e controle | D11: ='UsinaInfo'!D5 | E11: ='UsinaInfo'!F20 | F11: ='UsinaInfo'!G20 | G11: =E11-F11
B12: Mercado Livre | C12: microSD, LEDs e receptor: recotar Full; valores estimados | D12: ='Mercado Livre'!D5 | E12: ='Mercado Livre'!F14 | F12: ='Mercado Livre'!G14 | G12: =E12-F12
B13: Curto Circuito | C13: Módulo 4G LTE Cat-4 A7608SA-H (teleoperação remota) | D13: ='Curto Circuito'!D5 | E13: ='Curto Circuito'!F10 | F13: ='Curto Circuito'!G10 | G13: =E13-F13
B14: Total Consolidado | E14: =SUM(E11:E13) | F14: =SUM(F11:F13) | G14: =SUM(G11:G13)
B17: INVESTIMENTO POR CATEGORIA DE PRIORIDADE
B18: Prioridade | C18: Objetivo / Abrangência | D18: Total Cartão | E18: Total Pix/Boleto | F18: Participação
B19: Alta | C19: Térmica, tensão, antena condicional e 4G futuro | D19: =SUMIF(UsinaInfo!I8:I18,"Alta",UsinaInfo!F8:F18)+SUMIF('Mercado Livre'!I8:I11,"Alta",'Mercado Livre'!F8:F11)+SUMIF('Curto Circuito'!I8:I8,"Alta",'Curto Circuito'!F8:F8) | E19: =SUMIF(UsinaInfo!I8:I18,"Alta",UsinaInfo!G8:G18)+SUMIF('Mercado Livre'!I8:I11,"Alta",'Mercado Livre'!G8:G11)+SUMIF('Curto Circuito'!I8:I8,"Alta",'Curto Circuito'!G8:G8) | F19: =IF($B$6=0,"",D19/$B$6)
B20: Média | C20: Display OLED de bateria (UsinaInfo) | D20: =SUMIF(UsinaInfo!I8:I18,"Média",UsinaInfo!F8:F18)+SUMIF('Mercado Livre'!I8:I11,"Média",'Mercado Livre'!F8:F11)+SUMIF('Curto Circuito'!I8:I8,"Média",'Curto Circuito'!F8:F8) | E20: =SUMIF(UsinaInfo!I8:I18,"Média",UsinaInfo!G8:G18)+SUMIF('Mercado Livre'!I8:I11,"Média",'Mercado Livre'!G8:G11)+SUMIF('Curto Circuito'!I8:I8,"Média",'Curto Circuito'!G8:G8) | F20: =IF($B$6=0,"",D20/$B$6)
B21: Baixa | C21: Controle futuro + itens ML ainda estimados | D21: =SUMIF(UsinaInfo!I8:I18,"Baixa",UsinaInfo!F8:F18)+SUMIF('Mercado Livre'!I8:I11,"Baixa",'Mercado Livre'!F8:F11)+SUMIF('Curto Circuito'!I8:I8,"Baixa",'Curto Circuito'!F8:F8) | E21: =SUMIF(UsinaInfo!I8:I18,"Baixa",UsinaInfo!G8:G18)+SUMIF('Mercado Livre'!I8:I11,"Baixa",'Mercado Livre'!G8:G11)+SUMIF('Curto Circuito'!I8:I8,"Baixa",'Curto Circuito'!G8:G8) | F21: =IF($B$6=0,"",D21/$B$6)
B22: Total Consolidado | D22: =SUM(D19:D21) | E22: =SUM(E19:E21) | F22: =SUM(F19:F21)
B24: Compra pendente | C24: 3 anúncios ML sem Full confirmado. Antena e receptor dependem do modelo da placa/rádio.
B25: Conjunto incompleto | C25: Farol sem limitador/acionamento/dissipação. Controle precisa de microcontrolador. Thermal pad não cotado.
B26: 4G / bancada | C26: Alimentação, interface, vídeo e encaixe do módulo ainda precisam de validação. Fretes e plano não incluídos.
B27: Subtotal lojas diretas | E27: =SUM(E11,E13) | F27: =SUM(F11,F13)

Sheet UsinaInfo
B2: USINAINFO — COMPONENTES DE BANCADA, SENSORES & CONTROLE
B3: Preços consultados em 13/10/2026. Montagem e compatibilidade ainda dependem de bancada.
B5: Desconto Boleto / Pix: | D5: 0.05 | E5: (editável)
B7: Código | C7: Produto | D7: Qtd | E7: Unit. Cartão | F7: Subtotal Cartão | G7: À Vista (Pix/Boleto) | H7: Link do Produto | I7: Prioridade | J7: Situação | K7: Uso / Compatibilidade Técnica
B8: 07459 | C8: Mini ventoinha 5V 25 × 25 × 10 mm | D8: 1 | E8: 16.97 | F8: =ROUND(D8*E8,2) | G8: =ROUND(F8*(1-$D$5),2) | H8: Abrir produto | I8: Alta | J8: Em estoque | K8: 5 V, 30–60 mA. Prever entrada/saída de ar. Ficha cita 25×25×10 mm; fotos mostram 7 mm: confirmar espessura.
B9: 06077 | C9: DS18B20 — sensor de temperatura digital | D9: 2 | E9: 15.34 | F9: =ROUND(D9*E9,2) | G9: =ROUND(F9*(1-$D$5),2) | H9: Abrir produto | I9: Alta | J9: Em estoque | K9: Componente avulso. Prever pull-up 4,7 kΩ e isolamento. Medir região quente da câmera e ambiente; não mede a junção.
B10: 07479 | C10: Kit de 3 dissipadores autoadesivos | D10: 1 | E10: 3.6 | F10: =ROUND(D10*E10,2) | G10: =ROUND(F10*(1-$D$5),2) | H10: Abrir produto | I10: Alta | J10: Em estoque | K10: 3 peças por kit. Confirmar dimensões, contato térmico e isolamento. Não garante resfriamento da OV5640.
B11: 06731 | C11: Sensor de tensão DC 0–25 V (divisor 5:1) | D11: 1 | E11: 4.95 | F11: =ROUND(D11*E11,2) | G11: =ROUND(F11*(1-$D$5),2) | H11: Abrir produto | I11: Alta | J11: Em estoque | K11: Divisor 5:1 para A0 do Nano. Alternativa ao divisor já documentado. Calibrar; tensão não fornece % exata de carga.
B12: 08359 | C12: Kit Antena Wi-Fi 2,4GHz 3dBi + Cabo Pigtail U.FL (IPEX1) para SMA Fêmea | D12: 1 | E12: 11.8 | F12: =ROUND(D12*E12,2) | G12: =ROUND(F12*(1-$D$5),2) | H12: Abrir produto | I12: Alta | J12: Compatibilidade pendente | K12: Kit completo: inclui a antena de 3dBi e o cabo adaptador Pigtail U.FL para rosca SMA fêmea.
B13: 08483 | C13: Display OLED 0,96” I²C 128×64 (SSD1306) | D13: 1 | E13: 24.3 | F13: =ROUND(D13*E13,2) | G13: =ROUND(F13*(1-$D$5),2) | H13: Abrir produto | I13: Média | J13: Em estoque | K13: Nano: A4/A5. Conferir disponibilidade. SSD1306 com framebuffer usa 1 kB; preferir buffer de página U8g2 (U8g2 não é sempre leve).
B14: 08712 | C14: Display TFT 1,3” ST7789 SPI 240×240 | D14: 1 | E14: 34.7 | F14: =ROUND(D14*E14,2) | G14: =ROUND(F14*(1-$D$5),2) | H14: Abrir produto | I14: Baixa | J14: Em estoque | K14: Controle futuro. Precisa de microcontrolador disponível no laboratório; TFT sozinho não recebe vídeo nem envia comandos.
B15: 05623 | C15: Joystick analógico KY-023 / HW-504 | D15: 2 | E15: 5.95 | F15: =ROUND(D15*E15,2) | G15: =ROUND(F15*(1-$D$5),2) | H15: Abrir produto | I15: Baixa | J15: Em estoque | K15: Dois joysticks, cada um com dois eixos + botão. No ESP alimentar em 3,3 V; não conectar saídas 5 V ao ADC.
B16: 03741 | C16: Conversor de nível lógico 3,3V / 5V bidirecional — CNL35 | D16: 1 | E16: 7.5 | F16: =ROUND(D16*E16,2) | G16: =ROUND(F16*(1-$D$5),2) | H16: Abrir produto | I16: Alta | J16: Em estoque | K16: Adaptação 3,3 V (ESP32) ⇄ 5 V (Nano) para UART nativa a 115200 baud, eliminando o transistor BC337.
B17: 09989 | C17: Display TFT LCD 3,5" SPI Touch Screen com Slot SD (ILI9488) | D17: 1 | E17: 119.6 | F17: =ROUND(D17*E17,2) | G17: =ROUND(F17*(1-$D$5),2) | H17: Abrir produto | I17: Alta | J17: Em estoque | K17: Display grande 480x320 com touch screen (XPT2046) e slot MicroSD, lógica nativa 3,3 V via SPI.
B18: 02989 | C18: Push Button Chave Táctil 6x6x5mm (2x Kits com 5 un = 10 botões) | D18: 2 | E18: 2.46 | F18: =ROUND(D18*E18,2) | G18: =ROUND(F18*(1-$D$5),2) | H18: Abrir produto | I18: Alta | J18: Em estoque | K18: 10 chaves tácteis momentâneas para comandos físicos, reset, calibração e botões de interface.
C20: Total dos itens cotados (UsinaInfo) | F20: =SUM(F8:F18) | G20: =SUM(G8:G18)
C21: Subtotal Prioridade Alta (cotados) | F21: =SUMIF(I8:I18,"Alta",F8:F18) | G21: =SUMIF(I8:I18,"Alta",G8:G18)
C22: Subtotal Prioridade Média (cotados) | F22: =SUMIF(I8:I18,"Média",F8:F18) | G22: =SUMIF(I8:I18,"Média",G8:G18)
C23: Subtotal Prioridade Baixa (cotados) | F23: =SUMIF(I8:I18,"Baixa",F8:F18) | G23: =SUMIF(I8:I18,"Baixa",G8:G18)
B25: Notas e Observações:
B26: • ¹ Desconto à vista de 5% configurável na célula D5. Fretes não inclusos.
B27: Preços dos 8 itens conferidos; sensor DC: valor consultado nesta sessão. Estoque pode mudar.
B28: W5500 e ESP auxiliar ausentes nesta versão; controle futuro precisa de placa disponível no laboratório.
B29: Thermal pad não consta nesta lista. Verificar espessura e área de contato antes de cotar.

Sheet Mercado Livre
B2: MERCADO LIVRE — COMPONENTES DE EXPANSÃO (PRIORIDADE BAIXA)
B3: Ofertas ainda a recotar com vendedor e item específicos. Links atuais não comprovam Full.
B5: Desconto Boleto / Pix: | D5: 0 | E5: (Preço padrão cartão/Pix)
B7: Código | C7: Produto | D7: Qtd | E7: Unit. estimado | F7: Subtotal Cartão | G7: À Vista (Pix/Boleto) | H7: Link do Produto | I7: Prioridade | J7: Situação | K7: Uso / Compatibilidade Técnica
B8: ML-SD32 | C8: Cartão microSD SanDisk Ultra 32GB Classe 10 + Adaptador | D8: 1 | E8: 44.9 | F8: =ROUND(D8*E8,2) | G8: =ROUND(F8*(1-$D$5),2) | H8: Revisar anúncio | I8: Baixa | J8: A recotar Full | K8: R$44,90 não confirmado. Link abriu a R$59 sem Full. Confirmar slot/firmware SD; gravação contínua não implementada/validada.
B9: ML-LED3W | C9: Kit 10x LEDs 3W Branco Frio 6000K c/ Base Estrela | D9: 1 | E9: 29.9 | F9: =ROUND(D9*E9,2) | G9: =ROUND(F9*(1-$D$5),2) | H9: Revisar anúncio | I9: Baixa | J9: A recotar Full | K9: R$29,90 não confirmado; anúncio abriu a R$70,13 sem Full confirmado. Corrente não validada. Farol exige limitador, PWM e dissipação dedicada.
B10: ML-FSIA6B | C10: Receptor FlySky FS-iA6B 6CH 2.4GHz AFHDS 2A | D10: 1 | E10: 79.9 | F10: =ROUND(D10*E10,2) | G10: =ROUND(F10*(1-$D$5),2) | H10: Revisar anúncio | I10: Baixa | J10: Importado; não elegível | K10: Preço estimado sem cotação elegível. AFHDS 2A: confirmar modelo do FlySky. Marca/procedência do anúncio não comprovam receptor oficial. Integrar ao Nano + failsafe.
B11: ML-MAX98357A | C11: Módulo amplificador I2S MAX98357A + Mini alto-falante 3W | D11: 1 | E11: 25 | F11: =ROUND(D11*E11,2) | G11: =ROUND(F11*(1-$D$5),2) | H11: Revisar anúncio | I11: Média | J11: A recotar Full | K11: DAC + amplificador Classe D 3,2 W via I2S nativo do ESP32 (3 pinos) para buzina real, efeitos sonoros e alertas.
C14: Total estimado (não validado) | F14: =SUM(F8:F11) | G14: =SUM(G8:G11)
C15: Subtotal prioridade média (estimado) | F15: =SUMIF(I8:I11,"Média",F8:F11) | G15: =SUMIF(I8:I11,"Média",G8:G11)
C16: Subtotal prioridade baixa (estimado) | F16: =SUMIF(I8:I11,"Baixa",F8:F11) | G16: =SUMIF(I8:I11,"Baixa",G8:G11)
B18: Notas e Observações ML:
B19: Catálogo MLB/MLBU não garante Full. Registrar oferta, vendedor e Full na seção de compra.
B20: Driver ausente: o farol só fica completo com limitação de corrente, acionamento e dissipação dimensionados.
B21: Prioridades desta versão preservadas. Valores estimados mantidos; não são cotações aprovadas.

Sheet Curto Circuito
B2: CURTO CIRCUITO — EXPANSÃO TELEMETRIA 4G / LTE
B3: Módulo LTE Cat-4 para expansão futura; ligação com a S3-CAM ainda a validar.
B5: Desconto Boleto / Pix: | D5: 0.1 | E5: (editável)
B7: Código | C7: Produto | D7: Qtd | E7: Unit. Cartão | F7: Subtotal Cartão | G7: À Vista (Pix/Boleto) | H7: Link do Produto | I7: Prioridade | J7: Situação | K7: Uso / Compatibilidade Técnica
B8: 0000000018609 | C8: Módulo A7608SA-H 4G LTE Cat-4 + Antena FCP | D8: 1 | E8: 448 | F8: =ROUND(D8*E8,2) | G8: =ROUND(F8*(1-$D$5),2) | H8: Abrir produto | I8: Alta | J8: Cotado; integração pendente | K8: Placa 5–16 V, núcleo avulso 3,4–4,2 V. Reservar alimentação para picos; não assumir Mini-560 validado. USB/PPP, GPIO e vazão serial pendentes.
C10: Total Curto Circuito | F10: =SUM(F8) | G10: =SUM(G8)
B12: Notas e Observações:
B13: • ¹ Desconto à vista de 10% da Curto Circuito configurável na célula D5.
B14: • Frete e plano de dados móveis (M2M / IoT ou pré-pago) não inclusos no valor cotado.
B15: ML R$427,51: sem Full confirmado; alternativa excluída pelo requisito do usuário.
B17: Link Alternativa ML: | C17: ML sem Full confirmado
